raxodus/__init__.py
raxodus/cli.py
raxodus/client.py
raxodus/exceptions.py
raxodus/formatters.py
raxodus/models.py
raxodus/shell_completions.py
raxodus/version.py
raxodus-0.1.3.dist-info/METADATA
raxodus-0.1.3.dist-info/WHEEL
raxodus-0.1.3.dist-info/entry_points.txt
raxodus-0.1.3.dist-info/licenses/LICENSE
raxodus-0.1.3.dist-info/RECORD
