Metadata-Version: 2.4
Name: raxodus
Version: 0.1.3
Summary: Escape from Rackspace ticket hell - a minimal CLI for ticket management
Project-URL: Homepage, https://github.com/bdmorin/raxodus
Project-URL: Repository, https://github.com/bdmorin/raxodus
Project-URL: Issues, https://github.com/bdmorin/raxodus/issues
Author-email: Brian Morin <bdmorin@users.noreply.github.com>
License: MIT
License-File: LICENSE
Keywords: automation,cli,n8n,rackspace,tickets
Classifier: Development Status :: 3 - Alpha
Classifier: Environment :: Console
Classifier: Intended Audience :: System Administrators
Classifier: License :: OSI Approved :: MIT License
Classifier: Operating System :: OS Independent
Classifier: Programming Language :: Python :: 3
Classifier: Programming Language :: Python :: 3.10
Classifier: Programming Language :: Python :: 3.11
Classifier: Programming Language :: Python :: 3.12
Classifier: Topic :: System :: Systems Administration
Requires-Python: >=3.10
Requires-Dist: click>=8.1.0
Requires-Dist: httpx>=0.25.0
Requires-Dist: pydantic>=2.0.0
Requires-Dist: python-dateutil>=2.8.0
Requires-Dist: rich>=13.0.0
Requires-Dist: tenacity>=8.2.0
Provides-Extra: dev
Requires-Dist: mypy>=1.5.0; extra == 'dev'
Requires-Dist: pytest-httpx>=0.28.0; extra == 'dev'
Requires-Dist: pytest>=7.4.0; extra == 'dev'
Requires-Dist: ruff>=0.1.0; extra == 'dev'
